plexus/__init__.py
plexus/cli.py
plexus/client.py
plexus/config.py
plexus/connector.py
plexus/adapters/__init__.py
plexus/adapters/base.py
plexus/adapters/mqtt.py
plexus/adapters/registry.py
plexus/cameras/__init__.py
plexus/cameras/auto.py
plexus/cameras/base.py
plexus/cameras/picamera.py
plexus/cameras/usb.py
plexus/importers/__init__.py
plexus/importers/rosbag.py
plexus/sensors/__init__.py
plexus/sensors/auto.py
plexus/sensors/base.py
plexus/sensors/bme280.py
plexus/sensors/mpu6050.py
plexus_agent-0.3.13.dist-info/METADATA
plexus_agent-0.3.13.dist-info/WHEEL
plexus_agent-0.3.13.dist-info/entry_points.txt
plexus_agent-0.3.13.dist-info/licenses/LICENSE
plexus_agent-0.3.13.dist-info/RECORD
