Metadata-Version: 2.4
Name: plexus-agent
Version: 0.3.13
Summary: Send sensor data to Plexus in one line of code
Project-URL: Homepage, https://plexus.dev
Project-URL: Documentation, https://docs.plexus.dev
Project-URL: Repository, https://github.com/plexus-oss/agent
Project-URL: Issues, https://github.com/plexus-oss/agent/issues
Author-email: Plexus <hello@plexus.dev>
License-Expression: Apache-2.0
License-File: LICENSE
Keywords: hardware,iot,observability,robotics,sensors,telemetry
Classifier: Development Status :: 3 - Alpha
Classifier: Intended Audience :: Developers
Classifier: License :: OSI Approved :: Apache Software License
Classifier: Operating System :: OS Independent
Classifier: Programming Language :: Python :: 3
Classifier: Programming Language :: Python :: 3.8
Classifier: Programming Language :: Python :: 3.9
Classifier: Programming Language :: Python :: 3.10
Classifier: Programming Language :: Python :: 3.11
Classifier: Programming Language :: Python :: 3.12
Classifier: Topic :: Scientific/Engineering
Classifier: Topic :: System :: Hardware
Requires-Python: >=3.8
Requires-Dist: click>=8.0.0
Requires-Dist: requests>=2.28.0
Requires-Dist: websockets>=12.0
Provides-Extra: all
Requires-Dist: mcap>=1.0.0; extra == 'all'
Requires-Dist: numpy>=1.20.0; extra == 'all'
Requires-Dist: opencv-python>=4.8.0; extra == 'all'
Requires-Dist: paho-mqtt>=1.6.0; extra == 'all'
Requires-Dist: rosbags>=0.9.0; extra == 'all'
Requires-Dist: smbus2>=0.4.0; extra == 'all'
Provides-Extra: camera
Requires-Dist: numpy>=1.20.0; extra == 'camera'
Requires-Dist: opencv-python>=4.8.0; extra == 'camera'
Provides-Extra: dev
Requires-Dist: pytest; extra == 'dev'
Requires-Dist: pytest-cov; extra == 'dev'
Requires-Dist: ruff; extra == 'dev'
Provides-Extra: mqtt
Requires-Dist: paho-mqtt>=1.6.0; extra == 'mqtt'
Provides-Extra: picamera
Requires-Dist: picamera2>=0.3.12; extra == 'picamera'
Provides-Extra: ros
Requires-Dist: mcap>=1.0.0; extra == 'ros'
Requires-Dist: rosbags>=0.9.0; extra == 'ros'
Provides-Extra: sensors
Requires-Dist: smbus2>=0.4.0; extra == 'sensors'
Provides-Extra: video
Requires-Dist: numpy>=1.20.0; extra == 'video'
Requires-Dist: opencv-python>=4.8.0; extra == 'video'
